bsscripts/__init__.py
bsscripts/app.py
bsscripts/config.py
bsscripts/course_plugin.py
bsscripts/download.py
bsscripts/emails.py
bsscripts/logs.py
bsscripts/progress.py
bsscripts/scp.py
bsscripts/utils.py
bsscripts/commands/__init__.py
bsscripts/commands/check_grading.py
bsscripts/commands/distribute.py
bsscripts/commands/help.py
bsscripts/commands/list.py
bsscripts/commands/resend.py
bsscripts/data/grader/readme.txt
bsscripts/data/grader/data/bash-grading.sh
bsscripts/data/grader/data/upload-virtualenv.sh
bsscripts/data/grader/data/upload.py
bsscripts/data/grader/data/venv/CACHEDIR.TAG
bsscripts/data/grader/data/venv/pyvenv.cfg
bsscripts/data/grader/data/venv/bin/activate
bsscripts/data/grader/data/venv/bin/activate.csh
bsscripts/data/grader/data/venv/bin/activate.fish
bsscripts/data/grader/data/venv/bin/activate.nu
bsscripts/data/grader/data/venv/bin/activate.ps1
bsscripts/data/grader/data/venv/bin/activate_this.py
bsscripts/data/grader/data/venv/bin/normalizer
bsscripts/data/grader/data/venv/bin/pip
bsscripts/data/grader/data/venv/bin/pip-3.13
bsscripts/data/grader/data/venv/bin/pip3
bsscripts/data/grader/data/venv/bin/pip3.13
bsscripts/data/grader/data/venv/bin/python
bsscripts/data/grader/data/venv/bin/python3
bsscripts/data/grader/data/venv/bin/python3.13
bsscripts/data/grader/data/venv/lib/python3.13/site-packages/_virtualenv.pth
bsscripts/data/grader/data/venv/lib/python3.13/site-packages/_virtualenv.py
bsscripts/data/grader/data/venv/lib/python3.13/site-packages/pip-24.3.1.virtualenv
bsscripts/data/grader/data/venv/lib/python3.13/site-packages/__pycache__/_virtualenv.cpython-313.pyc
bsscripts/data/grader/data/venv/lib/python3.13/site-packages/bsapi/__init__.py
bsscripts/data/grader/data/venv/lib/python3.13/site-packages/bsapi/feedback.py
bsscripts/data/grader/data/venv/lib/python3.13/site-packages/bsapi/helper.py
bsscripts/data/grader/data/venv/lib/python3.13/site-packages/bsapi/identity.py
bsscripts/data/grader/data/venv/lib/python3.13/site-packages/urllib3-2.3.0.dist-info/licenses/LICENSE.txt
bsscripts-0.1.3.dist-info/LICENSE
bsscripts-0.1.3.dist-info/METADATA
bsscripts-0.1.3.dist-info/WHEEL
bsscripts-0.1.3.dist-info/entry_points.txt
bsscripts-0.1.3.dist-info/top_level.txt
bsscripts/data/grader/data/venv/lib/python3.13/site-packages/brightspace_api-1.0.3.dist-info/INSTALLER
bsscripts/data/grader/data/venv/lib/python3.13/site-packages/brightspace_api-1.0.3.dist-info/LICENSE
bsscripts/data/grader/data/venv/lib/python3.13/site-packages/brightspace_api-1.0.3.dist-info/METADATA
bsscripts/data/grader/data/venv/lib/python3.13/site-packages/brightspace_api-1.0.3.dist-info/RECORD
bsscripts/data/grader/data/venv/lib/python3.13/site-packages/brightspace_api-1.0.3.dist-info/REQUESTED
bsscripts/data/grader/data/venv/lib/python3.13/site-packages/brightspace_api-1.0.3.dist-info/WHEEL
bsscripts/data/grader/data/venv/lib/python3.13/site-packages/brightspace_api-1.0.3.dist-info/top_level.txt
bsscripts/data/grader/data/venv/lib/python3.13/site-packages/certifi-2025.1.31.dist-info/INSTALLER
bsscripts/data/grader/data/venv/lib/python3.13/site-packages/certifi-2025.1.31.dist-info/LICENSE
bsscripts/data/grader/data/venv/lib/python3.13/site-packages/certifi-2025.1.31.dist-info/METADATA
bsscripts/data/grader/data/venv/lib/python3.13/site-packages/certifi-2025.1.31.dist-info/RECORD
bsscripts/data/grader/data/venv/lib/python3.13/site-packages/certifi-2025.1.31.dist-info/WHEEL
bsscripts/data/grader/data/venv/lib/python3.13/site-packages/certifi-2025.1.31.dist-info/top_level.txt
bsscripts/data/grader/data/venv/lib/python3.13/site-packages/charset_normalizer-3.4.1.dist-info/INSTALLER
bsscripts/data/grader/data/venv/lib/python3.13/site-packages/charset_normalizer-3.4.1.dist-info/LICENSE
bsscripts/data/grader/data/venv/lib/python3.13/site-packages/charset_normalizer-3.4.1.dist-info/METADATA
bsscripts/data/grader/data/venv/lib/python3.13/site-packages/charset_normalizer-3.4.1.dist-info/RECORD
bsscripts/data/grader/data/venv/lib/python3.13/site-packages/charset_normalizer-3.4.1.dist-info/WHEEL
bsscripts/data/grader/data/venv/lib/python3.13/site-packages/charset_normalizer-3.4.1.dist-info/entry_points.txt
bsscripts/data/grader/data/venv/lib/python3.13/site-packages/charset_normalizer-3.4.1.dist-info/top_level.txt
bsscripts/data/grader/data/venv/lib/python3.13/site-packages/idna-3.10.dist-info/INSTALLER
bsscripts/data/grader/data/venv/lib/python3.13/site-packages/idna-3.10.dist-info/LICENSE.md
bsscripts/data/grader/data/venv/lib/python3.13/site-packages/idna-3.10.dist-info/METADATA
bsscripts/data/grader/data/venv/lib/python3.13/site-packages/idna-3.10.dist-info/RECORD
bsscripts/data/grader/data/venv/lib/python3.13/site-packages/idna-3.10.dist-info/WHEEL
bsscripts/data/grader/data/venv/lib/python3.13/site-packages/pip-24.3.1.dist-info/AUTHORS.txt
bsscripts/data/grader/data/venv/lib/python3.13/site-packages/pip-24.3.1.dist-info/INSTALLER
bsscripts/data/grader/data/venv/lib/python3.13/site-packages/pip-24.3.1.dist-info/LICENSE.txt
bsscripts/data/grader/data/venv/lib/python3.13/site-packages/pip-24.3.1.dist-info/METADATA
bsscripts/data/grader/data/venv/lib/python3.13/site-packages/pip-24.3.1.dist-info/RECORD
bsscripts/data/grader/data/venv/lib/python3.13/site-packages/pip-24.3.1.dist-info/WHEEL
bsscripts/data/grader/data/venv/lib/python3.13/site-packages/pip-24.3.1.dist-info/entry_points.txt
bsscripts/data/grader/data/venv/lib/python3.13/site-packages/pip-24.3.1.dist-info/top_level.txt
bsscripts/data/grader/data/venv/lib/python3.13/site-packages/requests-2.32.3.dist-info/INSTALLER
bsscripts/data/grader/data/venv/lib/python3.13/site-packages/requests-2.32.3.dist-info/LICENSE
bsscripts/data/grader/data/venv/lib/python3.13/site-packages/requests-2.32.3.dist-info/METADATA
bsscripts/data/grader/data/venv/lib/python3.13/site-packages/requests-2.32.3.dist-info/RECORD
bsscripts/data/grader/data/venv/lib/python3.13/site-packages/requests-2.32.3.dist-info/WHEEL
