Metadata-Version: 2.2
Name: bsscripts
Version: 0.1.3
Summary: Brightspace grading automation and management system.
Author-email: Ciske Harsema <Ciske.Harsema@ru.nl>, Job Doesburg <Job.Doesburg@ru.nl>
License: MIT License
Requires-Python: >=3.10
License-File: LICENSE
Requires-Dist: brightspace-api
Requires-Dist: patool
Requires-Dist: jsonschema
